pydantic_sqlalchemy_filter/__init__.py
pydantic_sqlalchemy_filter/base.py
pydantic_sqlalchemy_filter/interfaces/__init__.py
pydantic_sqlalchemy_filter/interfaces/query_builder.py
pydantic_sqlalchemy_filter/types.py
pydantic_sqlalchemy_filter-0.1.1.dist-info/LICENSE
pydantic_sqlalchemy_filter-0.1.1.dist-info/METADATA
pydantic_sqlalchemy_filter-0.1.1.dist-info/WHEEL
pydantic_sqlalchemy_filter-0.1.1.dist-info/RECORD
