Metadata-Version: 2.1
Name: pydantic-sqlalchemy-filter
Version: 0.1.1
Summary: Implement simple API filter interface for Sqlalchemy
Home-page: https://github.com/Deskent/pydantic_sqlalchemy_filter
License: MIT
Author: deskent
Author-email: battenetciz@gmail.com
Requires-Python: >=3.10,<4.0
Classifier: License :: OSI Approved :: MIT License
Classifier: Programming Language :: Python :: 3
Classifier: Programming Language :: Python :: 3.10
Classifier: Programming Language :: Python :: 3.11
Classifier: Programming Language :: Python :: 3.12
Classifier: Programming Language :: Python :: 3.13
Requires-Dist: pydantic (>=2.7.2,<3.0.0)
Requires-Dist: sqlalchemy (>=2.0.32,<3.0.0)
Project-URL: Repository, https://github.com/Deskent/pydantic_sqlalchemy_filter
